pwkeeper
