Metadata-Version: 1.1
Name: pwkeeper
Version: 1.1.0
Summary: Simple terminal-based password manager
Home-page: https://github.com/kvikshaug/pwkeeper/
Author: Ali Kaafarani
Author-email: ali@kvikshaug.no
License: WTFPL
Download-URL: https://github.com/kvikshaug/pwkeeper/tarball/v1.1.0
Keywords: password,password-manager,terminal
Platform: UNKNOWN
Classifier: Development Status :: 4 - Beta
Classifier: Intended Audience :: Developers
Classifier: Natural Language :: English
Classifier: Operating System :: POSIX
Classifier: Programming Language :: Python
Classifier: Programming Language :: Python :: 3
